mprib_tools/__init__.py
mprib_tools/__main__.py
mprib_tools/mprib_tools_script.py
mprib_tools/test_test.py
mprib_tools/system/__init__.py
mprib_tools/system/default_paths.py
mprib_tools/system/logging_configuration.py
mprib_tools-2023.1.1008.dist-info/entry_points.txt
mprib_tools-2023.1.1008.dist-info/LICENSE
mprib_tools-2023.1.1008.dist-info/WHEEL
mprib_tools-2023.1.1008.dist-info/METADATA
mprib_tools-2023.1.1008.dist-info/RECORD
